musicxml2fmf.py
musicxml2fmf-0.3.1.dist-info/entry_points.txt
musicxml2fmf-0.3.1.dist-info/WHEEL
musicxml2fmf-0.3.1.dist-info/METADATA
musicxml2fmf-0.3.1.dist-info/RECORD
