Metadata-Version: 2.1
Name: musicxml2fmf
Version: 0.3.1
Summary: MusicXML to Flipper Music Format
Home-page: https://github.com/white-gecko/musicxml2fmf
License: MIT
Keywords: music,converter,flipper-zero,flipper,musicxml
Author: Natanael Arndt
Author-email: arndtn@gmail.com
Requires-Python: >=3.8,<4.0
Classifier: Environment :: Console
Classifier: Intended Audience :: Developers
Classifier: Intended Audience :: Education
Classifier: Intended Audience :: End Users/Desktop
Classifier: License :: OSI Approved :: MIT License
Classifier: Operating System :: OS Independent
Classifier: Programming Language :: Python :: 3
Classifier: Programming Language :: Python :: 3.10
Classifier: Programming Language :: Python :: 3.8
Classifier: Programming Language :: Python :: 3.9
Classifier: Topic :: Games/Entertainment
Classifier: Topic :: Multimedia
Classifier: Topic :: Multimedia :: Sound/Audio
Classifier: Topic :: Multimedia :: Sound/Audio :: Conversion
Classifier: Topic :: Multimedia :: Sound/Audio :: Sound Synthesis
Classifier: Topic :: Utilities
Requires-Dist: black (>=22.6.0,<23.0.0)
Requires-Dist: click (>=8.1.3,<9.0.0)
Requires-Dist: lxml (>=4.9.1,<5.0.0)
Project-URL: Bug Tracker, https://github.com/white-gecko/musicxml2fmf/issues
Project-URL: Repository, https://github.com/white-gecko/musicxml2fmf
